Workbook

Sheet Analysis
A1: MONTHLY OPERATIONS REVIEW — BRANCH PERFORMANCE ANALYSIS
A2: Submitted by: Harinath Reddy Nallagondu | i360technologies Data Analyst Assessment | May 2026
A4: SECTION 1 — PROFITABILITY ANALYSIS
A5: Branch | B5: Total Sales ($) | C5: Operating Cost ($) | D5: Net Profit ($) | E5: Profit Margin (%) | F5: Performance | G5: Sentiment Rank
A6: Branch A | B6: 45000 | C6: 32000 | D6: =B6-C6 -> 13000 | E6: =D6/B6 -> 0.28888889 | F6: Moderate | G6: #2 — Good service
A7: Branch B | B7: 38500 | C7: 21000 | D7: =B7-C7 -> 17500 | E7: =D7/B7 -> 0.45454545 | F7: Best Performer ★ | G7: #1 — Best experience
A8: Branch C | B8: 52000 | C8: 48000 | D8: =B8-C8 -> 4000 | E8: =D8/B8 -> 0.076923077 | F8: Needs Improvement ⚠ | G8: #3 — Shipping issues
A9: TOTALS / AVERAGE | B9: =SUM(B6:B8) -> 135500 | C9: =SUM(C6:C8) -> 101000 | D9: =SUM(D6:D8) -> 34500 | E9: =AVERAGE(E6:E8) -> 0.27345247
A11: SECTION 2 — SENTIMENT ANALYSIS RANKING
A12: Rank | B12: Branch | C12: Customer Feedback
A13: 🥇 #1 | B13: Branch B | C13: Always has stock, friendly staff. | E13: Fully positive — no complaints raised
A14: 🥈 #2 | B14: Branch A | C14: Great service, but long queues. | E14: Strong service; queue is fixable
A15: 🥉 #3 | B15: Branch C | C15: Expensive shipping, slow delivery. | E15: Two pain points impacting loyalty
A17: SECTION 3 — BONUS CHALLENGE: BRANCH C COST REDUCTION (15%)
A18: Metric | B18: Current Value | C18: After 15% Reduction | D18: Change
A19: Operating Cost | B19: 48000 | C19: =B19*0.85 -> 40800 | D19: =B19*0.15*-1 -> -7200
A20: Net Profit | B20: 4000 | C20: =52000-C19 -> 11200 | D20: =C20-B20 -> 7200
A21: Profit Margin % | B21: =B20/52000 -> 0.076923077 | C21: =C20/52000 -> 0.21538462 | D21: =C21-B21 -> 0.13846154

Sheet Chart
A1: Branch | B1: Net Profit ($) | C1: Profit Margin (%)
A2: Branch A | B2: =Analysis!D6 -> 13000 | C2: =Analysis!E6 -> 0.28888889
A3: Branch B | B3: =Analysis!D7 -> 17500 | C3: =Analysis!E7 -> 0.45454545
A4: Branch C | B4: =Analysis!D8 -> 4000 | C4: =Analysis!E8 -> 0.076923077

Sheet Summary
A1: EXECUTIVE SUMMARY DASHBOARD
A4: Best Profit Margin | C4: Total Net Profit | E4: Needs Improvement
A5: =Analysis!E7 -> 0.45454545 | C5: =SUM(Analysis!D6:D8) -> 34500 | E5: =Analysis!E8 -> 0.076923077
A6: Branch B | C6: All Branches | E6: Branch C
A9: KEY RECOMMENDATIONS
A10: 🏆 Performance Bonus | B10: Branch B | C10: Highest margin (45.5%), best costs, best customer feedback
A11: 🔧 Process Improvement | B11: Branch C | C11: 7.7% margin despite $52K sales — fix shipping & reduce vendor costs
A12: 💡 Bonus Insight | B12: Branch C | C12: A 15% cost cut raises margin from 7.7% → 21.5% (profit: $4K → $11.2K)
